custom_study/__init__.py
custom_study-0.0.3.dist-info/DESCRIPTION.rst
custom_study-0.0.3.dist-info/METADATA
custom_study-0.0.3.dist-info/RECORD
custom_study-0.0.3.dist-info/WHEEL
custom_study-0.0.3.dist-info/metadata.json
custom_study-0.0.3.dist-info/top_level.txt
