Metadata-Version: 2.0
Name: custom-study
Version: 0.0.3
Summary: A Django admin theme with a horizontal, tabbed navigation bar
Home-page: http://github.com/
Author: Chris Rose
License: MIT
Platform: UNKNOWN
Classifier: Development Status :: 5 - Production/Stable
Classifier: Environment :: Web Environment
Classifier: Framework :: Django
Classifier: Intended Audience :: Developers
Classifier: Operating System :: OS Independent
Classifier: Programming Language :: Python
Classifier: Programming Language :: Python :: 3
Classifier: Programming Language :: Python :: 3.5
